lrslib/__init__.py
lrslib/tools.py
lrslib-1.0.6.2.dist-info/LICENSE
lrslib-1.0.6.2.dist-info/METADATA
lrslib-1.0.6.2.dist-info/WHEEL
lrslib-1.0.6.2.dist-info/top_level.txt
lrslib-1.0.6.2.dist-info/RECORD
