Metadata-Version: 2.1
Name: lrslib
Version: 1.0.6.2
Summary: 这是lrslib
Home-page: https://github.com/lrsgzs/lrslib
Author: Lrs
Author-email: liurongshuo2022@outlook.com
License: MIT
Project-URL: Github, https://github.com/lrsgzs/lrslib
Platform: UNKNOWN
Classifier: License :: OSI Approved :: MIT License
Classifier: Programming Language :: Python
Classifier: Programming Language :: Python :: 3
Classifier: Programming Language :: Python :: 3.7
Classifier: Programming Language :: Python :: Implementation :: CPython
Classifier: Programming Language :: Python :: Implementation :: PyPy
License-File: LICENSE
Requires-Dist: pygame
Requires-Dist: pillow
